examples/__init__.py
examples/core/__init__.py
examples/core/activations_visualization.py
examples/core/grad_cam.py
examples/core/gradients_inputs.py
examples/core/integrated_gradients.py
examples/core/occlusion_sensitivity.py
examples/core/smoothgrad.py
examples/core/vanilla_gradients.py
tests/__init__.py
tests/conftest.py
tests/callbacks/__init__.py
tests/callbacks/test_activations_visualization.py
tests/callbacks/test_grad_cam.py
tests/callbacks/test_integrated_gradients.py
tests/callbacks/test_occlusion_sensitivity.py
tests/callbacks/test_smoothgrad.py
tests/callbacks/test_vanilla_gradients.py
tests/core/__init__.py
tests/core/test_activations.py
tests/core/test_grad_cam.py
tests/core/test_gradients_inputs.py
tests/core/test_integrated_gradients.py
tests/core/test_occlusion_sensitivity.py
tests/core/test_smoothgrad.py
tests/core/test_vanilla_gradients.py
tests/integration/__init__.py
tests/integration/conftest.py
tests/integration/test_keras_api.py
tests/utils/__init__.py
tests/utils/test_display.py
tests/utils/test_image.py
tests/utils/test_saver.py
tf_explain/__init__.py
tf_explain/callbacks/__init__.py
tf_explain/callbacks/activations_visualization.py
tf_explain/callbacks/grad_cam.py
tf_explain/callbacks/gradients_inputs.py
tf_explain/callbacks/integrated_gradients.py
tf_explain/callbacks/occlusion_sensitivity.py
tf_explain/callbacks/smoothgrad.py
tf_explain/callbacks/vanilla_gradients.py
tf_explain/core/__init__.py
tf_explain/core/activations.py
tf_explain/core/grad_cam.py
tf_explain/core/gradients_inputs.py
tf_explain/core/integrated_gradients.py
tf_explain/core/occlusion_sensitivity.py
tf_explain/core/smoothgrad.py
tf_explain/core/vanilla_gradients.py
tf_explain/utils/__init__.py
tf_explain/utils/display.py
tf_explain/utils/image.py
tf_explain/utils/saver.py
tf_explain-0.3.1.dist-info/LICENCE
tf_explain-0.3.1.dist-info/METADATA
tf_explain-0.3.1.dist-info/WHEEL
tf_explain-0.3.1.dist-info/top_level.txt
tf_explain-0.3.1.dist-info/RECORD
