Metadata-Version: 2.1
Name: tf-explain
Version: 0.3.1
Summary: Interpretability Callbacks for Tensorflow 2.0
Home-page: https://github.com/sicara/tf-explain
Author: Raphaël Meudec
Author-email: raphaelm@sicara.com
License: MIT
Platform: UNKNOWN
Classifier: Development Status :: 3 - Alpha
Classifier: License :: OSI Approved :: MIT License
Classifier: Programming Language :: Python
Classifier: Programming Language :: Python :: 3
Classifier: Programming Language :: Python :: 3.6
Classifier: Programming Language :: Python :: 3.7
Classifier: Operating System :: OS Independent
Requires-Python: >=3.6
Provides-Extra: tests
Provides-Extra: publish
Provides-Extra: docs
License-File: LICENCE
